{
  "ticker": "2454.TW",
  "report_period_label": "2Q23",
  "report_period_end": "2023-06-30",
  "periods_in_report": [
    "2Q23",
    "1Q23",
    "2Q22"
  ],
  "source_id": "mediatek_press_release_2Q23",
  "source_url": null,
  "source_pdf_sha256": "f5c999a24a7cbe2402a875513ee4969e8eca9fc492f935928e0d5c689f7cf454",
  "source_pdf_bytes": 194545,
  "extracted_at": "2026-04-26T12:39:17+00:00",
  "fact_count": 51,
  "pages": [
    {
      "page": 1,
      "text": " \n \n                             July 28, 2023 \n  \n \n1\n2Q23 \nNote1: Non-TIFRS financial information should be considered in addition to, not as a substitute for, TIFRS \nfinancial information. Reconciliations between TIFRS and Non-TIFRS results include share-based \ncompensation, amortization of acquisition related assets, tax effect and other items. Further information is \nincluded in supplemental information.  \nMediaTek Inc. Reports Second-Quarter Consolidated Results \n \nMediaTek discloses Taiwan-International Financial Reporting Standards (TIFRS) financial \nmeasures and also provides Non-Taiwan-International Financial Reporting Standards \n(Non-TIFRS)Note1 financial measures as supplemental information. Non-TIFRS financial \ninformation should be considered in addition to, not as a substitute for, TIFRS financial \ninformation. Earnings distribution is made in accordance with financial statements based on \nTIFRS. \n    \nTaiwan-International Financial Reporting Standards (TIFRS) financial measures \n-2Q23 consolidated revenue of NT$98,135 million, up 2.6% quarter over quarter and down 37% \nyear-over-year  \n-2Q23 consolidated gross margin of 47.5%, down 0.5 percentage points quarter over quarter and \n1.8 percentage points year-over-year  \n-2Q23 consolidated net income of NT$16,019 million; EPS of NT$10.07 \n \nConsolidated Revenue \nMediaTek Inc. today announced financial results of second-quarter ended June 30, 2023. The second-quarter \nrevenue was NT$98,135 million, up 2.6% sequentially and down 37% year-over-year. The \nquarter-over-quarter increase was mainly due to improvements in demand for certain consumer electronics. \nThe year-over-year decrease was mainly due to customers’ inventory adjustments across all product lines \ncaused by weak end demand. \n \nConsolidated Gross Profit and Gross Margin  \nThe second-quarter gross profit was NT$46,646 million, up 1.6% sequentially and down 39.2% \nyear-over-year. Gross margin for the quarter was 47.5%, down 0.5 percentage points from the previous \nquarter and 1.8 percentage points from the year-ago quarter. The quarter-over-quarter and year-over-year \ndecreases reflected changes in prices and costs of our products.  \n \nConsolidated Operating Expenses \nOperating expenses for the quarter was NT$31,896 million (32.5% of revenue), compared with NT$31,543 \nmillion (33% of revenue) in the previous quarter and NT$37,583 million (24.1% of revenue) in the same \nperiod last year. Operating expenses for the quarter were nearly flat compared to the previous quarter. The \nyear-over-year decrease was mainly due to lower employee profit sharing expenses in this quarter. \nOperating expenses for the quarter included: \n- R&D expenses of NT$26,188 million (26.7% of revenue), decreased from NT$26,483 million in the \nprevious quarter and NT$30,180 million in the year-ago quarter. \n- Selling expenses of NT$3,375 million (3.4% of revenue), increased from NT$2,699 million in the \nprevious quarter and decreased from NT$3,636 million in the year-ago quarter. \n"
    },
    {
      "page": 2,
      "text": " \n \n                             July 28, 2023 \n \n2\n2Q23 \n- Administration expenses of NT$2,333 million (2.4% of revenue), decreased from NT$2,361 million in \nthe previous quarter and NT$3,768 million in the year-ago quarter. \n \nConsolidated Operating Income and Operating Margin  \nOperating income for the quarter was NT$14,751 million, up 2.7% sequentially and down 62.4% \nyear-over-year. Operating margin for the quarter was 15%, the same as the previous quarter and down from \n25.2% in the year-ago quarter. \n \nConsolidated Non-operating Income (loss) and Income Tax  \nNon-operating income for the quarter was NT$3,620 million, or 3.7% of revenue, mainly from interest income \nand dividend income. Income tax expense for the quarter was NT$2,351 million. \n \nConsolidated Net Income, Net Profit Margin and EPS  \nNet income for the quarter was NT$16,019 million, down 5.2% sequentially and 55% year-over-year. Net \nprofit margin for the quarter was 16.3%, decreased from 17.7% in the previous quarter and 22.9% in the \nyear-ago quarter. EPS was NT$10.07, down from NT$10.64 in the prior quarter and NT$22.39 in the year-ago \nquarter. The quarter-over-quarter decreases in net income, net profit margin and EPS were mainly due to \nhigher non-operating income last quarter. The year-over-year decreases in net income, net profit margin and \nEPS were mainly due to lower revenue and gross margin in this quarter. \n \nConsolidated Cash and Financial Assets-Current  \nCash and financial assets-current at the end of the quarter was NT$192,428 million. This represents 29.1% of \nthe company’s total assets. Cash and financial assets-current was NT$154,710 million and NT$256,547 million \nat the end of previous quarter and the year-ago quarter, respectively. Financial assets-current portfolio \nincludes mutual funds, bonds, derivatives and so on. \n \nConsolidated Accounts Receivable \nAccounts receivable (net) at the end of the quarter was NT$45,639 million. The accounts receivable turnover \nwas 43 days based on quarterly average net receivables divided by annualized net revenue. The turnover was \nhigher than 42 days in the previous quarter and 37 days in the year-ago quarter. \n \nConsolidated Inventory \nNet inventory at the end of the quarter was NT$61,067 million. The inventory turnover was 115 days based on \nquarterly average inventory divided by annualized cost of goods sold. The turnover was lower than 128 days \nin the previous quarter and higher than 104 days in the year-ago quarter. \n \nConsolidated Cash Flow from Operations  \nNet cash provided by operating activities during the quarter was NT$46,732 million, compared with NT$2,858 \nmillion in the previous quarter and NT$35,554 million in the year-ago quarter. \n"
    },
    {
      "page": 3,
      "text": " \n \n                             July 28, 2023 \n \n3\n2Q23 \nEarnings Webcast \nMediaTek will hold a public webcast today (July 28). Materials for the conference call will be published 30 \nminutes prior to the call and an audio replay will be available in one hour after the call at the investors \nsection of MediaTek’s website.  \nhttps://corp.mediatek.com/investor-relations/financial-information/quarterly-earnings \n \nSchedule: \nDate: Friday, July 28, 2023 \nTime: 3:00 – 4:00 p.m. (Taiwan Time)  \nLanguage: English \n \nWebcast Links: \nhttps://webpage-ott2b.cdn.hinet.net/webpage/live?contentProvider=mediatek \n \nInvestors who want to raise questions may use the toll number below. \nDial-in Number: +852-21121444 / +886-2-33961191  \nPassword: 9909528# \n \n \nAbout MediaTek Inc. \nMediaTek Incorporated (TWSE: 2454) is a global fabless semiconductor company that enables nearly 2 \nbillion connected devices a year. We are a market leader in developing innovative systems-on-chip (SoC) for \nmobile device, home entertainment, connectivity and IoT products. Our dedication to innovation has \npositioned us as a driving market force in several key technology areas, including highly power-efficient \nmobile technologies, automotive solutions and a broad range of advanced multimedia products such as \nsmartphones, tablets, digital televisions, 5G, Voice Assistant Devices (VAD) and wearables. MediaTek \nempowers and inspires people to expand their horizons and achieve their goals through smart technology, \nmore easily and efficiently than ever before. We work with the brands you love to make great technology \naccessible to everyone, and it drives everything we do. Visit www.mediatek.com for more information.  \n \n \n \n"
    },
    {
      "page": 4,
      "text": " \n \n                             July 28, 2023 \n \n4\n2Q23 \nTaiwan-International Financial Reporting Standards (TIFRS) \nMediaTek Inc. \nConsolidated Income Statement (Unaudited) \n \n(In NT$ millions, except EPS)     \n2Q23 \n \n1Q23 \n \n2Q22 \nQ-Q \nY-Y \nNet Sales \n98,135  \n95,652  \n155,730 \n2.6% \n(37.0%) \nOperating costs \n(51,489)  \n(49,739)  \n(78,966) \n \n \nGross profit \n46,646  \n45,912  \n76,764 \n1.6% \n(39.2%) \n  Selling expenses \n(3,375)  \n(2,699)  \n(3,636) \n \n \n  Administration expenses \n(2,333)  \n(2,361)  \n(3,768) \n \n \n  R&D expenses \n(26,188)  \n(26,483)  \n(30,180) \n \n \nOperating expenses \n(31,896)  \n(31,543)  \n(37,583) \n \n \nOperating income \n14,751  \n14,369  \n39,181 \n2.7% \n(62.4%) \nNet non-operating income  \n3,620  \n4,735  \n1,756 \n \n \nNet income before income tax \n18,370  \n19,104  \n40,937 \n \n \n  Income tax expense \n(2,351)  \n(2,213)  \n(5,325) \n \n \nNet income \n16,019  \n16,890  \n35,612 \n(5.2%) \n(55.0%) \n  Owners of the parent \n15,965  \n16,874  \n35,437 \n(5.4%) \n(54.9%) \n  Non-controlling interests \n54  \n17  \n175 \n  \nEPS attributable to the \nparent(NT$) \n10.07  \n10.64  \n22.39 \n \n \nAverage Exchange Rate - USD/NTD \n30.70 \n \n30.40 \n \n29.44 \n \n \nNote: Sums may not equal totals due to rounding. \n   \nMediaTek Inc. \nConsolidated Income Statement (Percentage of Revenue) \n \n \n2Q23 \n1Q23 \n2Q22 \nGross profit \n47.5% \n48.0% \n49.3% \n  Selling expenses \n(3.4%)   \n(2.8%)   \n(2.3%)   \n  Administration expenses \n(2.4%)   \n(2.5%)   \n(2.4%)   \n  R&D expenses \n(26.7%)   \n(27.7%)   \n(19.4%)   \nOperating income \n15.0% \n15.0% \n25.2% \n  Non-operating income  \n3.7%  \n5.0%  \n1.1%  \n  Income tax expense \n(2.4%)   \n(2.3%)   \n(3.4%)   \nNet income \n16.3% \n17.7% \n22.9% \nNote: Sums may not equal totals due to rounding.  \n"
    },
    {
      "page": 5,
      "text": " \n \n                             July 28, 2023 \n \n5\n2Q23 \nMediaTek Inc. \nConsolidated Balance Sheet (Unaudited) \n \n(In NT$ millions) \n2Q23 \n1Q23 \n2Q22 \nCash & financial assets-current \n192,428 \n154,710 \n256,547 \nAccounts receivable \n45,639 \n46,311 \n61,899 \nInventories \n61,067 \n69,265 \n91,410 \nOther current assets \n19,005 \n21,173 \n14,579 \nFunds and investments \n149,829 \n131,226 \n124,679 \nIntangible assets \n81,053 \n78,375 \n73,662 \nOther non-current assets \n111,663 \n111,326 \n107,966 \nTotal assets \n660,684 \n612,385 \n730,742 \nShort-term loans \n4,450 \n4,600 \n41,291 \nAccounts payable \n29,555 \n21,169 \n45,328 \nOther current liabilities \n233,801 \n221,138 \n234,301 \nTotal non-current liabilities  \n26,461 \n26,506 \n17,026 \nTotal equity \n366,417 \n338,972 \n392,797 \nNote: Sums may not equal totals due to rounding. \n \n \n \nMediaTek Inc. \nConsolidated Cash Flow Summary (Unaudited) \n \n(In NT$ millions) \n2Q23 \n1Q23 \n2Q22 \nNet cash provided by (used in) operating activities \n46,732 \n2,858 \n35,554 \nNet cash provided by (used in) investing activities \n(11,262) \n(9,955) \n(12,678) \nNet cash provided by (used in) financing activities \n(321) \n667 \n(19,712) \nEffect of changes in exchange rate on cash and cash equivalents \n3,249 \n(1,375) \n4,621 \nNet increase (decrease) in cash and cash equivalents \n38,398 \n(7,806) \n7,785 \nCash and cash equivalents at the end of the period \n178,094 \n139,696 \n238,218 \nNote: Sums may not equal totals due to rounding. \n \n \n"
    },
    {
      "page": 6,
      "text": " \n \n                             July 28, 2023 \n \n6\n2Q23 \n【Supplemental Information】 \nReconciliations of TIFRS Results to Non-TIFRS ResultsNote2 \n \n(In NT$ millions) \n2Q23 \n1Q23 \n2Q22 \nQ-Q \nY-Y \nTIFRS \nOperating income  \n14,751 \n14,369 \n39,181 \n2.7%  \n(62.4%) \nOperating income margin(%) \n15.0% \n15.0% \n25.2% \n  \n  \nReconciliations \nShare-based compensation  \n561 \n566 \n1,248 \n  \n  \nAmortization of acquisition related assets  \n119 \n126 \n90 \n  \n  \nNon-TIFRS \nOperating income  \n15,430 15,061 40,519 \n2.5%  \n(61.9%) \nOperating income margin (%) \n15.7% 15.7% 26.0% \n  \n  \n \n \n \n \n \n \n \nTIFRS \nNet income \n16,019 \n16,890 \n35,612 (5.2%)  (55.0%) \nNet income margin(%) \n16.3% \n17.7% \n22.9% \n  \n  \n  Net income- Owners of the parent \n15,965 \n16,874 \n35,437 (5.4%)  (54.9%) \nEPS(NT$) \n10.07 \n10.64 \n22.39 \n \n  \nReconciliations \nShare-based compensation  \n561 \n566 \n1,248 \n  \n  \nAmortization of acquisition related assets  \n119 \n126 \n90 \n \n  \nTax effect \n(94) \n(94) \n(185) \n  \n  \nNon-TIFRS \nNet income  \n16,605 17,488 36,765 (5.1%)  (54.8%) \nNet income margin (%) \n16.9% 18.3% 23.6% \n  \n  \n  Net income- Owners of the parent \n16,526 17,449 36,569 (5.3%)  (54.8%) \nEPS(NT$) \n10.42 \n11.00 \n23.10 \n  \n  \nNote1: Sums may not equal totals due to rounding. \nNote2: Non-TIFRS financial information should be considered in addition to, not as a substitute for, TIFRS \nfinancial information. Reconciliations between TIFRS and Non-TIFRS results include share-based compensation, \namortization of acquisition related assets, tax effect and other items. Earnings distribution is made in \naccordance with financial statements based on TIFRS. \n \n \n \n \n \n \n \n"
    }
  ]
}